rockset_sqlalchemy/__init__.py
rockset_sqlalchemy/connection.py
rockset_sqlalchemy/cursor.py
rockset_sqlalchemy/exceptions.py
rockset_sqlalchemy/sqlalchemy/__init__.py
rockset_sqlalchemy/sqlalchemy/compiler.py
rockset_sqlalchemy/sqlalchemy/dialect.py
rockset_sqlalchemy/sqlalchemy/types.py
rockset_sqlalchemy-0.0.1.dist-info/LICENSE
rockset_sqlalchemy-0.0.1.dist-info/METADATA
rockset_sqlalchemy-0.0.1.dist-info/WHEEL
rockset_sqlalchemy-0.0.1.dist-info/entry_points.txt
rockset_sqlalchemy-0.0.1.dist-info/top_level.txt
rockset_sqlalchemy-0.0.1.dist-info/RECORD
