Metadata-Version: 2.1
Name: rockset-sqlalchemy
Version: 0.0.1
Summary: Rockset's SQLAlchemy support and DB-API specification
Home-page: https://github.com/rockset/rockset-sqlalchemy
Author: Rockset
Author-email: support@rockset.com
Keywords: Rockset,rockset-client
Classifier: Programming Language :: Python :: 3
Classifier: License :: OSI Approved :: Apache Software License
Classifier: Operating System :: OS Independent
License-File: LICENSE
Requires-Dist: rockset (>=1.0.0)
Requires-Dist: sqlalchemy (<2.0.0,>=1.4.0)
